filterx-0.4.1.data/scripts/filterx
filterx-0.4.1.dist-info/METADATA
filterx-0.4.1.dist-info/WHEEL
filterx-0.4.1.dist-info/licenses/LICENSE
filterx/__init__.py
filterx/__main__.py
filterx-0.4.1.dist-info/RECORD
