Metadata-Version: 2.4
Name: filterx
Version: 0.4.1
License-File: LICENSE
Summary: A command line tool to filter data by using python-like syntax
Home-Page: https://github.com/dwpeng/filterx
Requires-Python: >=3.8
Project-URL: homepage, https://github.com/dwpeng/filterx
Project-URL: repository, https://github.com/dwpeng/filterx
Project-URL: documentation, https://filterx.dwpeng.com
